{
  "db_name": "PostgreSQL",
  "query": "\n        SELECT id, password_hash\n        FROM users\n        WHERE username = $1\n        ",
  "describe": {
    "columns": [
      {
        "ordinal": 0,
        "name": "id",
        "type_info": "Uuid"
      },
      {
        "ordinal": 1,
        "name": "password_hash",
        "type_info": "Varchar"
      }
    ],
    "parameters": {
      "Left": [
        "Text"
      ]
    },
    "nullable": [
      false,
      false
    ]
  },
  "hash": "c4757196c55a7ad972698d29ee806294b89a4738d557117628db23b6a30ecdf7"
}
